funAD/__init__.py
funAD/__main__.py
funAD/dual_number.py
funAD/function.py
funAD/operations.py
funAD/optimizers.py
funAD-1.0.3.dist-info/LICENSE
funAD-1.0.3.dist-info/METADATA
funAD-1.0.3.dist-info/WHEEL
funAD-1.0.3.dist-info/top_level.txt
funAD-1.0.3.dist-info/RECORD
