Metadata-Version: 2.1
Name: funAD
Version: 1.0.3
Summary: an automatic differentiation package created by AC207 students
Author-email: Hanlin Zhu <hzhu@g.harvard.edu>, Xu Tang <xutang@g.harvard.edu>, Tiantong Li <tiantongli@g.harvard.edu>, Zhecheng Yao <zhechengyao@g.harvard.edu>
Project-URL: Homepage, https://code.harvard.edu/CS107/team21
Classifier: Programming Language :: Python :: 3
Classifier: License :: OSI Approved :: BSD License
Classifier: Topic :: Software Development :: Testing
Requires-Python: >=3.5
License-File: LICENSE
Requires-Dist: numpy
